Metadata-Version: 1.2
Name: memorize
Version: 0.1.1
Summary: A caching package with options for timed caching and caching aware rate limiting
Home-page: https://github.com/saporitigianni/memorize
Author: Gianni Saporiti
Author-email: saporitigianni@outlook.com
License: BSD
Download-URL: https://pypi.python.org/pypi/memorize
Keywords: cache,caching,decorator,rate-limit,timeout,timer
Platform: UNKNOWN
Classifier: Development Status :: 4 - Beta
Classifier: Intended Audience :: Developers
Classifier: License :: OSI Approved :: BSD License
Classifier: Operating System :: OS Independent
Classifier: Programming Language :: Python :: 3
Classifier: Topic :: Software Development :: Build Tools
Classifier: Topic :: Internet
Classifier: Topic :: Internet :: WWW/HTTP
Classifier: Topic :: System :: Networking
Requires-Python: >=3
